geography_guessing/main.py
geography_guessing-0.0.3.dist-info/LICENSE.txt
geography_guessing-0.0.3.dist-info/METADATA
geography_guessing-0.0.3.dist-info/WHEEL
geography_guessing-0.0.3.dist-info/entry_points.txt
geography_guessing-0.0.3.dist-info/top_level.txt
geography_guessing-0.0.3.dist-info/RECORD
